AUTHORS
LICENSE
MANIFEST.in
README.rst
setup.py
django_payonline.egg-info/PKG-INFO
django_payonline.egg-info/SOURCES.txt
django_payonline.egg-info/dependency_links.txt
django_payonline.egg-info/top_level.txt
payonline/__init__.py
payonline/forms.py
payonline/helpers.py
payonline/models.py
payonline/settings.py
payonline/urls.py
payonline/views.py
payonline/fields/__init__.py
payonline/fields/forms.py
payonline/fields/models.py