Metadata-Version: 1.0
Name: django-payonline
Version: 0.1.1
Summary: A Django application for integration with PayOnline System
Home-page: UNKNOWN
Author: Mike Yumatov
Author-email: mike@yumatov.org
License: ISC
Platform: UNKNOWN
Classifier: Development Status :: 4 - Beta
Classifier: Framework :: Django
Classifier: Intended Audience :: Developers
Classifier: License :: OSI Approved :: ISC License (ISCL)
Classifier: Programming Language :: Python
Classifier: Programming Language :: Python :: 2.5
Classifier: Programming Language :: Python :: 2.6
Classifier: Programming Language :: Python :: 2.7
Classifier: Topic :: Internet :: WWW/HTTP
